{"cameraMode":{"drawMode":0,"name":"Shaded","section":"Shading Mode"},"sceneLighting":true,"audioPlay":false,"sceneViewState":{"m_AlwaysRefresh":false,"showFog":true,"showSkybox":true,"showFlares":true,"showImageEffects":true,"showParticleSystems":true,"showVisualEffectGraphs":true,"m_FxEnabled":true},"in2DMode":false,"pivot":{"x":-6.319331169128418,"y":2.8458926677703859,"z":-47.529720306396487},"rotation":{"x":-0.0340825617313385,"y":0.8702607154846191,"z":-0.004015142563730478,"w":0.495077520608902},"size":1.3659722805023194,"orthographic":false}